RealstatsModelRollout/__init__.py
RealstatsModelRollout/auth.py
RealstatsModelRollout/global_functions.py
RealstatsModelRollout/model.py
RealstatsModelRollout/settings.py
RealstatsModelRollout/validate.py
RealstatsModelRollout/versioning.py
RealstatsModelRollout/vmachine.py
RealstatsModelRollout-0.2.2.dist-info/LICENSE.md
RealstatsModelRollout-0.2.2.dist-info/METADATA
RealstatsModelRollout-0.2.2.dist-info/WHEEL
RealstatsModelRollout-0.2.2.dist-info/top_level.txt
RealstatsModelRollout-0.2.2.dist-info/RECORD
