Metadata-Version: 2.1
Name: RealstatsModelRollout
Version: 0.2.2
Summary: Realstats model version control
Home-page: https://github.com/bharkema/RealstatsModelRollout
Download-URL: https://github.com/bharkema/RealstatsModelRollout/archive/v0.2.2.tar.gz
Author: Bowen
Author-email: b.harkema@clappform.com
License: MIT
Keywords: model validation
Classifier: Development Status :: 5 - Production/Stable
Classifier: License :: OSI Approved :: MIT License
Classifier: Programming Language :: Python :: 3
Classifier: Operating System :: OS Independent
License-File: LICENSE.md
Requires-Dist: pandas
Requires-Dist: pyarrow
Requires-Dist: pygithub
